ownca/__init__.py
ownca/__version__.py
ownca/_constants.py
ownca/exceptions.py
ownca/ownca.py
ownca/utils.py
ownca/crypto/__init__.py
ownca/crypto/certs.py
ownca/crypto/keys.py
OwnCA-0.4.0.dist-info/LICENSE
OwnCA-0.4.0.dist-info/METADATA
OwnCA-0.4.0.dist-info/WHEEL
OwnCA-0.4.0.dist-info/top_level.txt
OwnCA-0.4.0.dist-info/RECORD
