Metadata-Version: 2.1
Name: OwnCA
Version: 0.4.0
Summary: Python Own Certificate Authority
Home-page: https://github.com/OwnCA/ownca
Author: Kairo de Araujo
Author-email: kairo@dearaujo.nl
License: Apache 2.0
Project-URL: documentation, https://ownca.readthedocs.io
Project-URL: repository, https://github.com/OwnCA/ownca
Keywords: ownca,Certificate Authority,CA,certificates
Classifier: Development Status :: 4 - Beta
Classifier: Intended Audience :: Developers
Classifier: Natural Language :: English
Classifier: License :: OSI Approved :: Apache Software License
Classifier: Programming Language :: Python
Classifier: Programming Language :: Python :: 3.7
Classifier: Programming Language :: Python :: 3.8
Classifier: Programming Language :: Python :: 3.9
Classifier: Programming Language :: Python :: 3.10
Classifier: Programming Language :: Python :: Implementation :: CPython
Classifier: Programming Language :: Python :: Implementation :: PyPy
Requires-Python: >=3.7
License-File: LICENSE
Requires-Dist: cryptography (<35.0.0,>=3.4.6)
Requires-Dist: voluptuous (>=0.11.7)
Provides-Extra: dev
Requires-Dist: pytest ; extra == 'dev'
Requires-Dist: coverage (==5.1) ; extra == 'dev'
Requires-Dist: tox ; extra == 'dev'
Requires-Dist: flake8 ; extra == 'dev'
Requires-Dist: codecov ; extra == 'dev'
Requires-Dist: sphinx ; extra == 'dev'
Requires-Dist: sphinx-rtd-theme ; extra == 'dev'
Requires-Dist: twine ; extra == 'dev'
Requires-Dist: mypy ; extra == 'dev'
Requires-Dist: isort ; extra == 'dev'
Requires-Dist: black (==21.12b0) ; extra == 'dev'
Requires-Dist: pre-commit ; extra == 'dev'
